{
    "name": "calibration_5000000000.0_Hz",
    "attrs": {},
    "components": [
        {
            "name": "two_port_oscilloscope",
            "attrs": {},
            "ports": [
                {
                    "name": "CH1",
                    "attrs": {},
                    "parent_component_name": ""
                },
                {
                    "name": "CH2",
                    "attrs": {},
                    "parent_component_name": ""
                }
            ],
            "connections": [],
            "components": [],
            "metrics": []
        },
        {
            "name": "two_port_oscilloscope",
            "attrs": {},
            "ports": [
                {
                    "name": "CH1",
                    "attrs": {},
                    "parent_component_name": ""
                }
            ],
            "connections": [],
            "components": [],
            "metrics": []
        },
        {
            "name": "power_splitter_1to2",
            "attrs": {},
            "ports": [
                {
                    "name": "IN",
                    "attrs": {},
                    "parent_component_name": ""
                },
                {
                    "name": "OUT1",
                    "attrs": {},
                    "parent_component_name": ""
                },
                {
                    "name": "OUT2",
                    "attrs": {},
                    "parent_component_name": ""
                }
            ],
            "connections": [],
            "components": [],
            "metrics": []
        }
    ],
    "connections": [
        {
            "name": "",
            "attrs": {},
            "ports": [
                {
                    "name": "OUT1",
                    "attrs": {},
                    "parent_component_name": ""
                },
                {
                    "name": "CH1",
                    "attrs": {},
                    "parent_component_name": ""
                }
            ],
            "time": {
                "name": "",
                "attrs": {},
                "value": 0,
                "mean": 0,
                "min": 0,
                "max": 0,
                "standard_deviation": 0,
                "count": null,
                "unit": {
                    "name": "second",
                    "datum": "second",
                    "base": 1,
                    "label": "Time $s$"
                }
            }
        },
        {
            "name": "",
            "attrs": {},
            "ports": [
                {
                    "name": "OUT2",
                    "attrs": {},
                    "parent_component_name": ""
                },
                {
                    "name": "CH2",
                    "attrs": {},
                    "parent_component_name": ""
                }
            ],
            "time": {
                "name": "",
                "attrs": {},
                "value": 0,
                "mean": 0,
                "min": 0,
                "max": 0,
                "standard_deviation": 0,
                "count": null,
                "unit": {
                    "name": "second",
                    "datum": "second",
                    "base": 1,
                    "label": "Time $s$"
                }
            }
        }
    ],
    "goal": "",
    "parameters": {
        "square_wave_frequency_Hz": 5000000000.0
    },
    "index": 0,
    "date_configured": "",
    "date_measured": "",
    "measurement_configuration_list": []
}